tf_gen_models/__init__.py
tf_gen_models/version.py
tf_gen_models/algorithms/__init__.py
tf_gen_models/algorithms/gan/BceGAN.py
tf_gen_models/algorithms/gan/CramerGAN.py
tf_gen_models/algorithms/gan/GAN.py
tf_gen_models/algorithms/gan/WGAN.py
tf_gen_models/algorithms/gan/WGAN_ALP.py
tf_gen_models/algorithms/gan/WGAN_GP.py
tf_gen_models/algorithms/gan/__init__.py
tf_gen_models/algorithms/norm_flow/__init__.py
tf_gen_models/algorithms/vae/__init__.py
tf_gen_models/callbacks/CheckpointPrinter.py
tf_gen_models/callbacks/ImageSaver.py
tf_gen_models/callbacks/ModelSaver.py
tf_gen_models/callbacks/__init__.py
tf_gen_models/callbacks/schedulers/GanBaseLrScheduler.py
tf_gen_models/callbacks/schedulers/GanExpLrScheduler.py
tf_gen_models/callbacks/schedulers/GanPowLrScheduler.py
tf_gen_models/callbacks/schedulers/__init__.py
tf_gen_models/layers/__init__.py
tf_gen_models/metrics/__init__.py
tf_gen_models-0.0.12.dist-info/LICENSE
tf_gen_models-0.0.12.dist-info/METADATA
tf_gen_models-0.0.12.dist-info/WHEEL
tf_gen_models-0.0.12.dist-info/top_level.txt
tf_gen_models-0.0.12.dist-info/RECORD
